polymaps/__init__.py
polymaps/util.py
polymaps-0.0.108.dist-info/METADATA
polymaps-0.0.108.dist-info/WHEEL
polymaps-0.0.108.dist-info/top_level.txt
polymaps-0.0.108.dist-info/RECORD
