Metadata-Version: 2.1
Name: polymaps
Version: 0.0.108
Summary: A simple Python package to preprocess and postprocess LAMMPS simulations for polymers and small molecules
Home-page: https://gitlab.com/doublylinkedlist/polymaps/
Author: Xiaoli Yan
Author-email: xyan11@uic.edu
License: MIT
Requires-Dist: jupyter ==1.0.0
Requires-Dist: jupyterlab ==4.0.4
Requires-Dist: numpy ==1.25.0
Requires-Dist: scipy ==1.11.1
Requires-Dist: pandas ==2.0.2
Requires-Dist: matplotlib ==3.7.1
Requires-Dist: plotly ==5.15.0
Requires-Dist: scikit-learn ==1.3.0
